nanoconf/__init__.py
nanoconf/nanoconf.py
nanoconf-1.0.0.dist-info/LICENSE
nanoconf-1.0.0.dist-info/METADATA
nanoconf-1.0.0.dist-info/WHEEL
nanoconf-1.0.0.dist-info/top_level.txt
nanoconf-1.0.0.dist-info/RECORD
