Metadata-Version: 2.1
Name: nanoconf
Version: 1.0.0
Summary: The tiny opinionated config loader.
Author-email: Jacob J Callahan <jacob.callahan05@gmail.com>
Project-URL: Repository, https://github.com/JacobCallahan/nanoconf
Keywords: nanoconf,config,configuration,settings
Platform: any
Classifier: Development Status :: 5 - Production/Stable
Classifier: Intended Audience :: Developers
Classifier: Natural Language :: English
Classifier: Programming Language :: Python :: 3
Classifier: Programming Language :: Python :: 3.11
Classifier: Programming Language :: Python :: 3.12
Requires-Python: >=3.11
License-File: LICENSE
Requires-Dist: python-box
Requires-Dist: pyyaml
Provides-Extra: dev
Requires-Dist: black ; extra == 'dev'
Requires-Dist: pre-commit ; extra == 'dev'
Requires-Dist: pytest ; extra == 'dev'
Requires-Dist: ruff ; extra == 'dev'
Provides-Extra: setup
Requires-Dist: build ; extra == 'setup'
Requires-Dist: setuptools ; extra == 'setup'
Requires-Dist: twine ; extra == 'setup'
